sqlalchemy_tenant_wiper/__init__.py
sqlalchemy_tenant_wiper/core.py
sqlalchemy_tenant_wiper-0.1.8.dist-info/LICENSE
sqlalchemy_tenant_wiper-0.1.8.dist-info/METADATA
sqlalchemy_tenant_wiper-0.1.8.dist-info/WHEEL
sqlalchemy_tenant_wiper-0.1.8.dist-info/RECORD
