Metadata-Version: 2.3
Name: sqlalchemy-tenant-wiper
Version: 0.1.8
Summary: A flexible SQLAlchemy-based library for tenant data deletion in multi-tenant applications
License: MIT
Keywords: sqlalchemy,tenant,multi-tenant,database,deletion,cleanup
Author: Your Name
Author-email: your.email@example.com
Requires-Python: >=3.8,<4.0
Classifier: Development Status :: 4 - Beta
Classifier: Intended Audience :: Developers
Classifier: License :: OSI Approved :: MIT License
Classifier: Operating System :: OS Independent
Classifier: Programming Language :: Python :: 3
Classifier: Programming Language :: Python :: 3.8
Classifier: Programming Language :: Python :: 3.9
Classifier: Programming Language :: Python :: 3.10
Classifier: Programming Language :: Python :: 3.11
Classifier: Programming Language :: Python :: 3.12
Classifier: Programming Language :: Python :: 3.13
Classifier: Topic :: Database
Classifier: Topic :: Software Development :: Libraries :: Python Modules
Requires-Dist: SQLAlchemy (>=1.4.0,<2.0.0)
Project-URL: Documentation, https://github.com/timabilov/sqlalchemy-tenant-wiper#readme
Project-URL: Homepage, https://github.com/timabilov/sqlalchemy-tenant-wiper
Project-URL: Repository, https://github.com/timabilov/sqlalchemy-tenant-wiper
